main.py
setup.py
nuest.egg-info/PKG-INFO
nuest.egg-info/SOURCES.txt
nuest.egg-info/dependency_links.txt
nuest.egg-info/requires.txt
nuest.egg-info/top_level.txt